carconnectivity_connector_skoda-0.12.dist-info/licenses/LICENSE
carconnectivity_connectors/skoda/__init__.py
carconnectivity_connectors/skoda/_version.py
carconnectivity_connectors/skoda/capability.py
carconnectivity_connectors/skoda/charging.py
carconnectivity_connectors/skoda/climatization.py
carconnectivity_connectors/skoda/command_impl.py
carconnectivity_connectors/skoda/connector.py
carconnectivity_connectors/skoda/error.py
carconnectivity_connectors/skoda/mqtt_client.py
carconnectivity_connectors/skoda/vehicle.py
carconnectivity_connectors/skoda/auth/__init__.py
carconnectivity_connectors/skoda/auth/auth_util.py
carconnectivity_connectors/skoda/auth/my_skoda_session.py
carconnectivity_connectors/skoda/auth/openid_session.py
carconnectivity_connectors/skoda/auth/session_manager.py
carconnectivity_connectors/skoda/auth/skoda_web_session.py
carconnectivity_connectors/skoda/auth/helpers/blacklist_retry.py
carconnectivity_connectors/skoda/services/skoda_location_service.py
carconnectivity_connectors/skoda/ui/connector_ui.py
carconnectivity_connectors/skoda/ui/templates/skoda/status.html
carconnectivity_connector_skoda-0.12.dist-info/METADATA
carconnectivity_connector_skoda-0.12.dist-info/WHEEL
carconnectivity_connector_skoda-0.12.dist-info/top_level.txt
carconnectivity_connector_skoda-0.12.dist-info/RECORD
