Metadata-Version: 2.4
Name: carconnectivity-connector-skoda
Version: 0.12
Summary: CarConnectivity connector for Skoda services
Author: Till Steinbach
License-Expression: MIT
Classifier: Development Status :: 3 - Alpha
Classifier: Intended Audience :: Developers
Classifier: Programming Language :: Python :: 3.9
Classifier: Programming Language :: Python :: 3.10
Classifier: Programming Language :: Python :: 3.11
Classifier: Programming Language :: Python :: 3.12
Classifier: Programming Language :: Python :: 3.13
Classifier: Programming Language :: Python :: 3.14
Classifier: Topic :: Software Development :: Libraries
Requires-Python: >=3.9
License-File: LICENSE
Requires-Dist: carconnectivity>=0.11.6
Requires-Dist: oauthlib~=3.3.1
Requires-Dist: requests~=2.32.5
Requires-Dist: pyjwt~=2.10
Requires-Dist: paho-mqtt~=2.1.0
Dynamic: license-file
